LICENSE
MANIFEST.in
README.rst
setup.py
genrp/__init__.py
genrp/build.py
genrp/genrp.cpp
genrp/genrp.py
genrp/kernels.py
genrp/modeling.py
genrp/tests.py
genrp.egg-info/PKG-INFO
genrp.egg-info/SOURCES.txt
genrp.egg-info/dependency_links.txt
genrp.egg-info/requires.txt
genrp.egg-info/top_level.txt
genrp/include/genrp/banded.h
genrp/include/genrp/carma.h
genrp/include/genrp/exceptions.h
genrp/include/genrp/genrp.h
genrp/include/genrp/modeling.h
genrp/include/genrp/poly.h
genrp/include/genrp/utils.h
genrp/include/genrp/version.h
genrp/include/genrp/solver/band.h
genrp/include/genrp/solver/direct.h
genrp/include/genrp/solver/solver.h